crawl/__init__.py
crawl/dr_crawl.py
crawl/crawler/__init__.py
crawl/crawler/crawler.py
crawl/crawler/helpers.py
database/__init__.py
database/dr_add_tag.py
database/dr_append.py
database/dr_db_create.py
database/dr_db_down.py
database/dr_db_uninstall.py
database/dr_db_up.py
database/dr_gap.py
database/dr_import.py
database/dr_preview.py
database/dr_select.py
database/entities/__init__.py
database/entities/implication.py
database/entities/post.py
database/entities/tag.py
database/importer/__init__.py
database/importer/alias_importer.py
database/importer/importer.py
database/selector/__init__.py
database/selector/selected_sample.py
database/selector/selector.py
database/tag_normalizer/__init__.py
database/tag_normalizer/tag_normalizer.py
database/tag_normalizer/util.py
database/translator/__init__.py
database/translator/danbooru_translator.py
database/translator/e621_translator.py
database/translator/gelbooru_translator.py
database/translator/helpers.py
database/translator/rule34_translator.py
database/translator/translator.py
database/utils/__init__.py
database/utils/db_utils.py
database/utils/enums.py
database/utils/source_url.py
dataset/__init__.py
dataset/dr_build.py
dataset/dr_join.py
dataset/utils/__init__.py
dataset/utils/balance.py
dataset/utils/download.py
dataset/utils/format.py
dataset/utils/load.py
dataset/utils/prune.py
dataset/utils/resize.py
dataset/utils/selection_source.py
dataset/utils/split.py
tests/__init__.py
tests/test_balance.py
train/__init__.py
train/dr_convert_sd.py
train/dr_convert_sdxl.py
train/dr_train.py
train/dr_train_xl.py
train/vendor/__init__.py
train/vendor/huggingface/__init__.py
train/vendor/huggingface/diffusers/__init__.py
train/vendor/huggingface/diffusers/convert_diffusers_to_original_sdxl.py
train/vendor/huggingface/diffusers/convert_diffusers_to_original_stable_diffusion.py
train/vendor/huggingface/diffusers/resize_with_pad.py
train/vendor/huggingface/diffusers/train_text_to_image.py
DatasetRising-1.0.4.dist-info/LICENSE.md
DatasetRising-1.0.4.dist-info/METADATA
DatasetRising-1.0.4.dist-info/WHEEL
DatasetRising-1.0.4.dist-info/entry_points.txt
DatasetRising-1.0.4.dist-info/top_level.txt
DatasetRising-1.0.4.dist-info/RECORD
