Metadata-Version: 2.1
Name: DatasetRising
Version: 1.0.4
Summary: Toolchain for creating and training Stable Diffusion models with custom datasets
License: Copyright 2023 Mr. Stallion, Esq.
Project-URL: Homepage, https://github.com/hearmeneigh/dataset-rising
Project-URL: Bug Reports, https://github.com/hearmeneigh/dataset-rising/issues
Project-URL: Source, https://github.com/hearmeneigh/dataset-rising
Keywords: training,crawler,machine-learning,imageboard,booru,danbooru,ml,dataset,dataset-generation,gelbooru,e621,imagebooru,finetuning,mlops,huggingface,mlops-workflow,stable-diffusion,huggingface-users,diffusers,sdxl
Classifier: Development Status :: 5 - Production/Stable
Classifier: Environment :: Console
Classifier: Environment :: GPU
Classifier: Environment :: GPU :: NVIDIA CUDA
Classifier: Intended Audience :: Developers
Classifier: License :: OSI Approved :: MIT License
Classifier: Operating System :: MacOS
Classifier: Operating System :: POSIX
Classifier: Operating System :: POSIX :: Linux
Classifier: Programming Language :: Python :: 3
Classifier: Programming Language :: Python :: 3.8
Classifier: Programming Language :: Python :: 3.9
Classifier: Programming Language :: Python :: 3.10
Classifier: Programming Language :: Python :: 3.11
Classifier: Programming Language :: Python :: 3.12
Classifier: Topic :: Scientific/Engineering :: Artificial Intelligence
Classifier: Topic :: Scientific/Engineering :: Image Processing
Requires-Python: >=3.8
License-File: LICENSE.md
Requires-Dist: pymongo ==4.4.1
Requires-Dist: requests ==2.31.0
Requires-Dist: call-throttle ==0.3.0
Requires-Dist: furl ==2.1.2
Requires-Dist: ndjson ==0.3.1
Requires-Dist: anyascii ==0.3.2
Requires-Dist: pyyaml ==6.0.1
Requires-Dist: pyyaml-include ==1.3.1
Requires-Dist: halo ==0.0.31
Requires-Dist: jinja2 ==3.1.2
Requires-Dist: Pillow ==10.0.0
Requires-Dist: huggingface-hub ==0.17.3
Requires-Dist: transformers ==4.34.0
Requires-Dist: diffusers ==0.21.4
Requires-Dist: accelerate ==0.23.0
Requires-Dist: datasets ==2.14.5
Requires-Dist: torch ==2.0.1
Requires-Dist: torchvision ==0.15.2
Requires-Dist: pydash ==7.0.6
Requires-Dist: s3fs ==2023.1.0
Requires-Dist: bitsandbytes ==0.41.1
Requires-Dist: xformers ==0.0.22
